src/misspell/__init__.py
src/misspell/misspell.py
misspelled_generator-1.0.1.dist-info/METADATA
misspelled_generator-1.0.1.dist-info/WHEEL
misspelled_generator-1.0.1.dist-info/licenses/LICENSE.md
misspelled_generator-1.0.1.dist-info/RECORD
