Metadata-Version: 2.1
Name: misspelled_generator
Version: 1.0.1
Summary: This is a python library to generate slightly misspelled words compared to the original ones (currently works only on Latin alphabet)
Project-URL: Homepage, https://github.com/ngminhhoang1412/MisspelledGenerator
Project-URL: Bug Tracker, https://github.com/ngminhhoang1412/MisspelledGenerator/issues
Author-email: Mjho Nguyen <ngminhhoang1412@gmail.com>
License: MIT License
License-File: LICENSE.md
Classifier: License :: OSI Approved :: MIT License
Classifier: Operating System :: OS Independent
Classifier: Programming Language :: Python :: 3
Requires-Python: >=3.7
